odoo/addons/fieldservice_stock_request/README.rst
odoo/addons/fieldservice_stock_request/__init__.py
odoo/addons/fieldservice_stock_request/__manifest__.py
odoo/addons/fieldservice_stock_request/i18n/fieldservice_stock_request.pot
odoo/addons/fieldservice_stock_request/models/__init__.py
odoo/addons/fieldservice_stock_request/models/fsm_order.py
odoo/addons/fieldservice_stock_request/models/stock_move_line.py
odoo/addons/fieldservice_stock_request/models/stock_request.py
odoo/addons/fieldservice_stock_request/models/stock_request_order.py
odoo/addons/fieldservice_stock_request/readme/CONFIGURE.rst
odoo/addons/fieldservice_stock_request/readme/CONTRIBUTORS.rst
odoo/addons/fieldservice_stock_request/readme/CREDITS.rst
odoo/addons/fieldservice_stock_request/readme/DESCRIPTION.rst
odoo/addons/fieldservice_stock_request/readme/ROADMAP.rst
odoo/addons/fieldservice_stock_request/readme/USAGE.rst
odoo/addons/fieldservice_stock_request/security/ir.model.access.csv
odoo/addons/fieldservice_stock_request/static/description/icon.png
odoo/addons/fieldservice_stock_request/static/description/index.html
odoo/addons/fieldservice_stock_request/tests/__init__.py
odoo/addons/fieldservice_stock_request/tests/test_fsm_stock_request.py
odoo/addons/fieldservice_stock_request/views/fsm_order.xml
odoo/addons/fieldservice_stock_request/views/stock.xml
odoo/addons/fieldservice_stock_request/views/stock_request.xml
odoo/addons/fieldservice_stock_request/views/stock_request_order.xml
odoo12_addon_fieldservice_stock_request-12.0.2.0.0.dist-info/METADATA
odoo12_addon_fieldservice_stock_request-12.0.2.0.0.dist-info/WHEEL
odoo12_addon_fieldservice_stock_request-12.0.2.0.0.dist-info/top_level.txt
odoo12_addon_fieldservice_stock_request-12.0.2.0.0.dist-info/RECORD
